.gitignore
README.md
file.json
setup.cfg
setup.py
objectifier/__init__.py
python_objectifier.egg-info/PKG-INFO
python_objectifier.egg-info/SOURCES.txt
python_objectifier.egg-info/dependency_links.txt
python_objectifier.egg-info/top_level.txt