Metadata-Version: 2.1
Name: python-objectifier
Version: 1.5
Summary: objectifier
Home-page: https://github.com/xjxckk/python-objectifier/
Download-URL: https://github.com/xjxckk/python-objectifier/archive/refs/tags/v0.1.tar.gz
